{
	"_id" : ObjectId("58077f334a577b83ccd2445e"),
	"last_name" : "bear",
	"first_name" : "Kennif",
	"email" : "113@hotmail.com"
}
{
	"_id" : ObjectId("58077f334a577b83ccd2445f"),
	"last_name" : "Tayaysu",
	"first_name" : "Fajjak",
	"email" : "123343@yahoo.com"
}
{
	"_id" : ObjectId("58077f334a577b83ccd24460"),
	"last_name" : "Headed",
	"first_name" : "Shushed his",
	"email" : "1234567@gmail.com"
}
{
	"_id" : ObjectId("58077f334a577b83ccd24461"),
	"last_name" : "Li",
	"first_name" : "Li",
	"email" : "1582408888@qq.com"
}
{
	"_id" : ObjectId("58077f334a577b83ccd24462"),
	"last_name" : "richardson",
	"first_name" : "christopher",
	"email" : "1989christopherrichardson@gmail.com"
}

